[{"event_type": "kline", "event_time": 1720822224006, "symbol": "BTCUSDT", "kline_start_time": 1720822223000, "kline_close_time": 1720822223999, "interval": "1s", "first_trade_id": 3679854957, "last_trade_id": 3679854959, "open_price": 57644.0, "close_price": 57644.0, "high_price": 57644.0, "low_price": 57644.0, "base_asset_volume": 0.00157, "number_of_trades": 3, "is_kline_closed": true, "quote_asset_volume": 90.50108, "taker_buy_base_asset_volume": 0.0, "taker_buy_quote_asset_volume": 0.0, "ignore": "0"}, {"event_type": "kline", "event_time": 1720822225006, "symbol": "BTCUSDT", "kline_start_time": 1720822224000, "kline_close_time": 1720822224999, "interval": "1s", "first_trade_id": 3679854960, "last_trade_id": 3679854960, "open_price": 57644.0, "close_price": 57644.0, "high_price": 57644.0, "low_price": 57644.0, "base_asset_volume": 0.0009, "number_of_trades": 1, "is_kline_closed": true, "quote_asset_volume": 51.8796, "taker_buy_base_asset_volume": 0.0, "taker_buy_quote_asset_volume": 0.0, "ignore": "0"}, {"event_type": "kline", "event_time": 1720822226005, "symbol": "BTCUSDT", "kline_start_time": 1720822225000, "kline_close_time": 1720822225999, "interval": "1s", "first_trade_id": 3679854961, "last_trade_id": 3679855026, "open_price": 57644.0, "close_price": 57642.79, "high_price": 57644.0, "low_price": 57642.79, "base_asset_volume": 0.69985, "number_of_trades": 66, "is_kline_closed": true, "quote_asset_volume": 40342.1518008, "taker_buy_base_asset_volume": 0.00132, "taker_buy_quote_asset_volume": 76.0884828, "ignore": "0"}, {"event_type": "kline", "event_time": 1720822227005, "symbol": "BTCUSDT", "kline_start_time": 1720822226000, "kline_close_time": 1720822226999, "interval": "1s", "first_trade_id": 3679855027, "last_trade_id": 3679855028, "open_price": 57642.78, "close_price": 57642.79, "high_price": 57642.79, "low_price": 57642.78, "base_asset_volume": 0.00557, "number_of_trades": 2, "is_kline_closed": true, "quote_asset_volume": 321.0702862, "taker_buy_base_asset_volume": 0.00016, "taker_buy_quote_asset_volume": 9.2228464, "ignore": "0"}, {"event_type": "kline", "event_time": 1720822228005, "symbol": "BTCUSDT", "kline_start_time": 1720822227000, "kline_close_time": 1720822227999, "interval": "1s", "first_trade_id": 3679855029, "last_trade_id": 3679855030, "open_price": 57642.79, "close_price": 57642.78, "high_price": 57642.79, "low_price": 57642.78, "base_asset_volume": 0.00202, "number_of_trades": 2, "is_kline_closed": true, "quote_asset_volume": 116.4384295, "taker_buy_base_asset_volume": 0.00139, "taker_buy_quote_asset_volume": 80.1234781, "ignore": "0"}]