[{"event_type": "kline", "event_time": 1720822124006, "symbol": "BTCUSDT", "kline_start_time": 1720822123000, "kline_close_time": 1720822123999, "interval": "1s", "first_trade_id": -1, "last_trade_id": -1, "open_price": 57619.99, "close_price": 57619.99, "high_price": 57619.99, "low_price": 57619.99, "base_asset_volume": 0.0, "number_of_trades": 0, "is_kline_closed": true, "quote_asset_volume": 0.0, "taker_buy_base_asset_volume": 0.0, "taker_buy_quote_asset_volume": 0.0, "ignore": "0"}, {"event_type": "kline", "event_time": 1720822125006, "symbol": "BTCUSDT", "kline_start_time": 1720822124000, "kline_close_time": 1720822124999, "interval": "1s", "first_trade_id": -1, "last_trade_id": -1, "open_price": 57619.99, "close_price": 57619.99, "high_price": 57619.99, "low_price": 57619.99, "base_asset_volume": 0.0, "number_of_trades": 0, "is_kline_closed": true, "quote_asset_volume": 0.0, "taker_buy_base_asset_volume": 0.0, "taker_buy_quote_asset_volume": 0.0, "ignore": "0"}, {"event_type": "kline", "event_time": 1720822126006, "symbol": "BTCUSDT", "kline_start_time": 1720822125000, "kline_close_time": 1720822125999, "interval": "1s", "first_trade_id": 3679854650, "last_trade_id": 3679854661, "open_price": 57620.0, "close_price": 57620.0, "high_price": 57620.0, "low_price": 57619.99, "base_asset_volume": 0.16055, "number_of_trades": 12, "is_kline_closed": true, "quote_asset_volume": 9250.890995, "taker_buy_base_asset_volume": 0.16005, "taker_buy_quote_asset_volume": 9222.081, "ignore": "0"}, {"event_type": "kline", "event_time": 1720822127006, "symbol": "BTCUSDT", "kline_start_time": 1720822126000, "kline_close_time": 1720822126999, "interval": "1s", "first_trade_id": 3679854662, "last_trade_id": 3679854662, "open_price": 57620.0, "close_price": 57620.0, "high_price": 57620.0, "low_price": 57620.0, "base_asset_volume": 0.00054, "number_of_trades": 1, "is_kline_closed": true, "quote_asset_volume": 31.1148, "taker_buy_base_asset_volume": 0.00054, "taker_buy_quote_asset_volume": 31.1148, "ignore": "0"}, {"event_type": "kline", "event_time": 1720822128006, "symbol": "BTCUSDT", "kline_start_time": 1720822127000, "kline_close_time": 1720822127999, "interval": "1s", "first_trade_id": 3679854663, "last_trade_id": 3679854663, "open_price": 57620.0, "close_price": 57620.0, "high_price": 57620.0, "low_price": 57620.0, "base_asset_volume": 0.00023, "number_of_trades": 1, "is_kline_closed": true, "quote_asset_volume": 13.2526, "taker_buy_base_asset_volume": 0.00023, "taker_buy_quote_asset_volume": 13.2526, "ignore": "0"}]