[{"event_type": "kline", "event_time": 1720216135006, "symbol": "BTCUSDT", "kline_start_time": 1720216134000, "kline_close_time": 1720216134999, "interval": "1s", "first_trade_id": 3667109230, "last_trade_id": 3667109231, "open_price": 56681.11, "close_price": 56681.1, "high_price": 56681.11, "low_price": 56681.1, "base_asset_volume": 0.04553, "number_of_trades": 2, "is_kline_closed": true, "quote_asset_volume": 2580.6909242, "taker_buy_base_asset_volume": 0.04412, "taker_buy_quote_asset_volume": 2500.7705732, "ignore": "0"}, {"event_type": "kline", "event_time": 1720216136007, "symbol": "BTCUSDT", "kline_start_time": 1720216135000, "kline_close_time": 1720216135999, "interval": "1s", "first_trade_id": 3667109232, "last_trade_id": 3667109232, "open_price": 56681.11, "close_price": 56681.11, "high_price": 56681.11, "low_price": 56681.11, "base_asset_volume": 0.00035, "number_of_trades": 1, "is_kline_closed": true, "quote_asset_volume": 19.8383885, "taker_buy_base_asset_volume": 0.00035, "taker_buy_quote_asset_volume": 19.8383885, "ignore": "0"}, {"event_type": "kline", "event_time": 1720216137006, "symbol": "BTCUSDT", "kline_start_time": 1720216136000, "kline_close_time": 1720216136999, "interval": "1s", "first_trade_id": 3667109233, "last_trade_id": 3667109233, "open_price": 56681.1, "close_price": 56681.1, "high_price": 56681.1, "low_price": 56681.1, "base_asset_volume": 0.01968, "number_of_trades": 1, "is_kline_closed": true, "quote_asset_volume": 1115.484048, "taker_buy_base_asset_volume": 0.0, "taker_buy_quote_asset_volume": 0.0, "ignore": "0"}, {"event_type": "kline", "event_time": 1720216138006, "symbol": "BTCUSDT", "kline_start_time": 1720216137000, "kline_close_time": 1720216137999, "interval": "1s", "first_trade_id": 3667109234, "last_trade_id": 3667109237, "open_price": 56681.1, "close_price": 56681.1, "high_price": 56681.11, "low_price": 56681.1, "base_asset_volume": 0.00947, "number_of_trades": 4, "is_kline_closed": true, "quote_asset_volume": 536.7700222, "taker_buy_base_asset_volume": 0.00052, "taker_buy_quote_asset_volume": 29.4741772, "ignore": "0"}, {"event_type": "kline", "event_time": 1720216139006, "symbol": "BTCUSDT", "kline_start_time": 1720216138000, "kline_close_time": 1720216138999, "interval": "1s", "first_trade_id": 3667109238, "last_trade_id": 3667109238, "open_price": 56681.1, "close_price": 56681.1, "high_price": 56681.1, "low_price": 56681.1, "base_asset_volume": 0.001, "number_of_trades": 1, "is_kline_closed": true, "quote_asset_volume": 56.6811, "taker_buy_base_asset_volume": 0.0, "taker_buy_quote_asset_volume": 0.0, "ignore": "0"}, {"event_type": "kline", "event_time": 1720216140006, "symbol": "BTCUSDT", "kline_start_time": 1720216139000, "kline_close_time": 1720216139999, "interval": "1s", "first_trade_id": 3667109239, "last_trade_id": 3667109244, "open_price": 56681.11, "close_price": 56681.11, "high_price": 56681.11, "low_price": 56681.1, "base_asset_volume": 0.01304, "number_of_trades": 6, "is_kline_closed": true, "quote_asset_volume": 739.1216726, "taker_buy_base_asset_volume": 0.01286, "taker_buy_quote_asset_volume": 728.9190746, "ignore": "0"}, {"event_type": "kline", "event_time": 1720216141007, "symbol": "BTCUSDT", "kline_start_time": 1720216140000, "kline_close_time": 1720216140999, "interval": "1s", "first_trade_id": 3667109245, "last_trade_id": 3667109247, "open_price": 56681.1, "close_price": 56681.11, "high_price": 56681.11, "low_price": 56681.1, "base_asset_volume": 0.02763, "number_of_trades": 3, "is_kline_closed": true, "quote_asset_volume": 1566.0990605, "taker_buy_base_asset_volume": 0.02675, "taker_buy_quote_asset_volume": 1516.2196925, "ignore": "0"}, {"event_type": "kline", "event_time": 1720216142006, "symbol": "BTCUSDT", "kline_start_time": 1720216141000, "kline_close_time": 1720216141999, "interval": "1s", "first_trade_id": -1, "last_trade_id": -1, "open_price": 56681.11, "close_price": 56681.11, "high_price": 56681.11, "low_price": 56681.11, "base_asset_volume": 0.0, "number_of_trades": 0, "is_kline_closed": true, "quote_asset_volume": 0.0, "taker_buy_base_asset_volume": 0.0, "taker_buy_quote_asset_volume": 0.0, "ignore": "0"}, {"event_type": "kline", "event_time": 1720216143006, "symbol": "BTCUSDT", "kline_start_time": 1720216142000, "kline_close_time": 1720216142999, "interval": "1s", "first_trade_id": -1, "last_trade_id": -1, "open_price": 56681.11, "close_price": 56681.11, "high_price": 56681.11, "low_price": 56681.11, "base_asset_volume": 0.0, "number_of_trades": 0, "is_kline_closed": true, "quote_asset_volume": 0.0, "taker_buy_base_asset_volume": 0.0, "taker_buy_quote_asset_volume": 0.0, "ignore": "0"}, {"event_type": "kline", "event_time": 1720216144006, "symbol": "BTCUSDT", "kline_start_time": 1720216143000, "kline_close_time": 1720216143999, "interval": "1s", "first_trade_id": 3667109248, "last_trade_id": 3667109253, "open_price": 56681.1, "close_price": 56681.11, "high_price": 56681.11, "low_price": 56681.1, "base_asset_volume": 0.0595, "number_of_trades": 6, "is_kline_closed": true, "quote_asset_volume": 3372.5254511, "taker_buy_base_asset_volume": 0.00011, "taker_buy_quote_asset_volume": 6.2349221, "ignore": "0"}, {"event_type": "kline", "event_time": 1720216145005, "symbol": "BTCUSDT", "kline_start_time": 1720216144000, "kline_close_time": 1720216144999, "interval": "1s", "first_trade_id": 3667109254, "last_trade_id": 3667109254, "open_price": 56681.11, "close_price": 56681.11, "high_price": 56681.11, "low_price": 56681.11, "base_asset_volume": 0.00026, "number_of_trades": 1, "is_kline_closed": true, "quote_asset_volume": 14.7370886, "taker_buy_base_asset_volume": 0.00026, "taker_buy_quote_asset_volume": 14.7370886, "ignore": "0"}, {"event_type": "kline", "event_time": 1720216146006, "symbol": "BTCUSDT", "kline_start_time": 1720216145000, "kline_close_time": 1720216145999, "interval": "1s", "first_trade_id": 3667109255, "last_trade_id": 3667109255, "open_price": 56681.1, "close_price": 56681.1, "high_price": 56681.1, "low_price": 56681.1, "base_asset_volume": 0.00013, "number_of_trades": 1, "is_kline_closed": true, "quote_asset_volume": 7.368543, "taker_buy_base_asset_volume": 0.0, "taker_buy_quote_asset_volume": 0.0, "ignore": "0"}, {"event_type": "kline", "event_time": 1720216147006, "symbol": "BTCUSDT", "kline_start_time": 1720216146000, "kline_close_time": 1720216146999, "interval": "1s", "first_trade_id": 3667109256, "last_trade_id": 3667109257, "open_price": 56681.11, "close_price": 56681.11, "high_price": 56681.11, "low_price": 56681.11, "base_asset_volume": 0.00428, "number_of_trades": 2, "is_kline_closed": true, "quote_asset_volume": 242.5951508, "taker_buy_base_asset_volume": 0.00428, "taker_buy_quote_asset_volume": 242.5951508, "ignore": "0"}, {"event_type": "kline", "event_time": 1720216148006, "symbol": "BTCUSDT", "kline_start_time": 1720216147000, "kline_close_time": 1720216147999, "interval": "1s", "first_trade_id": 3667109258, "last_trade_id": 3667109258, "open_price": 56681.11, "close_price": 56681.11, "high_price": 56681.11, "low_price": 56681.11, "base_asset_volume": 0.00053, "number_of_trades": 1, "is_kline_closed": true, "quote_asset_volume": 30.0409883, "taker_buy_base_asset_volume": 0.00053, "taker_buy_quote_asset_volume": 30.0409883, "ignore": "0"}, {"event_type": "kline", "event_time": 1720216149006, "symbol": "BTCUSDT", "kline_start_time": 1720216148000, "kline_close_time": 1720216148999, "interval": "1s", "first_trade_id": 3667109259, "last_trade_id": 3667109271, "open_price": 56681.1, "close_price": 56681.1, "high_price": 56681.11, "low_price": 56681.1, "base_asset_volume": 0.02547, "number_of_trades": 13, "is_kline_closed": true, "quote_asset_volume": 1443.667846, "taker_buy_base_asset_volume": 0.0229, "taker_buy_quote_asset_volume": 1297.997419, "ignore": "0"}, {"event_type": "kline", "event_time": 1720216150006, "symbol": "BTCUSDT", "kline_start_time": 1720216149000, "kline_close_time": 1720216149999, "interval": "1s", "first_trade_id": 3667109272, "last_trade_id": 3667109272, "open_price": 56681.11, "close_price": 56681.11, "high_price": 56681.11, "low_price": 56681.11, "base_asset_volume": 0.00025, "number_of_trades": 1, "is_kline_closed": true, "quote_asset_volume": 14.1702775, "taker_buy_base_asset_volume": 0.00025, "taker_buy_quote_asset_volume": 14.1702775, "ignore": "0"}, {"event_type": "kline", "event_time": 1720216151006, "symbol": "BTCUSDT", "kline_start_time": 1720216150000, "kline_close_time": 1720216150999, "interval": "1s", "first_trade_id": 3667109273, "last_trade_id": 3667109274, "open_price": 56681.11, "close_price": 56681.1, "high_price": 56681.11, "low_price": 56681.1, "base_asset_volume": 0.0117, "number_of_trades": 2, "is_kline_closed": true, "quote_asset_volume": 663.1689829, "taker_buy_base_asset_volume": 0.01129, "taker_buy_quote_asset_volume": 639.9297319, "ignore": "0"}, {"event_type": "kline", "event_time": 1720216152006, "symbol": "BTCUSDT", "kline_start_time": 1720216151000, "kline_close_time": 1720216151999, "interval": "1s", "first_trade_id": 3667109275, "last_trade_id": 3667109276, "open_price": 56681.11, "close_price": 56681.1, "high_price": 56681.11, "low_price": 56681.1, "base_asset_volume": 0.00048, "number_of_trades": 2, "is_kline_closed": true, "quote_asset_volume": 27.2069295, "taker_buy_base_asset_volume": 0.00015, "taker_buy_quote_asset_volume": 8.5021665, "ignore": "0"}, {"event_type": "kline", "event_time": 1720216153006, "symbol": "BTCUSDT", "kline_start_time": 1720216152000, "kline_close_time": 1720216152999, "interval": "1s", "first_trade_id": 3667109277, "last_trade_id": 3667109277, "open_price": 56681.11, "close_price": 56681.11, "high_price": 56681.11, "low_price": 56681.11, "base_asset_volume": 0.0003, "number_of_trades": 1, "is_kline_closed": true, "quote_asset_volume": 17.004333, "taker_buy_base_asset_volume": 0.0003, "taker_buy_quote_asset_volume": 17.004333, "ignore": "0"}, {"event_type": "kline", "event_time": 1720216154007, "symbol": "BTCUSDT", "kline_start_time": 1720216153000, "kline_close_time": 1720216153999, "interval": "1s", "first_trade_id": 3667109278, "last_trade_id": 3667109282, "open_price": 56681.1, "close_price": 56681.1, "high_price": 56681.11, "low_price": 56681.1, "base_asset_volume": 0.23056, "number_of_trades": 5, "is_kline_closed": true, "quote_asset_volume": 13068.3967186, "taker_buy_base_asset_volume": 0.23026, "taker_buy_quote_asset_volume": 13051.3923886, "ignore": "0"}]