[{"event_type": "kline", "event_time": 1720862785004, "symbol": "BTCUSDT", "kline_start_time": 1720862784000, "kline_close_time": 1720862784999, "interval": "1s", "first_trade_id": 3680207144, "last_trade_id": 3680207149, "open_price": 58128.01, "close_price": 58128.02, "high_price": 58128.02, "low_price": 58128.01, "base_asset_volume": 0.0955, "number_of_trades": 6, "is_kline_closed": true, "quote_asset_volume": 5551.224959, "taker_buy_base_asset_volume": 0.0004, "taker_buy_quote_asset_volume": 23.251208, "ignore": "0"}, {"event_type": "kline", "event_time": 1720862786005, "symbol": "BTCUSDT", "kline_start_time": 1720862785000, "kline_close_time": 1720862785999, "interval": "1s", "first_trade_id": 3680207150, "last_trade_id": 3680207151, "open_price": 58128.01, "close_price": 58128.01, "high_price": 58128.01, "low_price": 58128.01, "base_asset_volume": 0.00271, "number_of_trades": 2, "is_kline_closed": true, "quote_asset_volume": 157.5269071, "taker_buy_base_asset_volume": 0.0, "taker_buy_quote_asset_volume": 0.0, "ignore": "0"}, {"event_type": "kline", "event_time": 1720862787005, "symbol": "BTCUSDT", "kline_start_time": 1720862786000, "kline_close_time": 1720862786999, "interval": "1s", "first_trade_id": 3680207152, "last_trade_id": 3680207181, "open_price": 58128.01, "close_price": 58125.12, "high_price": 58128.01, "low_price": 58125.12, "base_asset_volume": 0.27732, "number_of_trades": 30, "is_kline_closed": true, "quote_asset_volume": 16119.8460454, "taker_buy_base_asset_volume": 0.0, "taker_buy_quote_asset_volume": 0.0, "ignore": "0"}, {"event_type": "kline", "event_time": 1720862788005, "symbol": "BTCUSDT", "kline_start_time": 1720862787000, "kline_close_time": 1720862787999, "interval": "1s", "first_trade_id": 3680207182, "last_trade_id": 3680207202, "open_price": 58124.34, "close_price": 58122.6, "high_price": 58124.34, "low_price": 58122.6, "base_asset_volume": 0.46262, "number_of_trades": 21, "is_kline_closed": true, "quote_asset_volume": 26888.8868428, "taker_buy_base_asset_volume": 0.0001, "taker_buy_quote_asset_volume": 5.812261, "ignore": "0"}, {"event_type": "kline", "event_time": 1720862789005, "symbol": "BTCUSDT", "kline_start_time": 1720862788000, "kline_close_time": 1720862788999, "interval": "1s", "first_trade_id": 3680207203, "last_trade_id": 3680207542, "open_price": 58122.6, "close_price": 58120.02, "high_price": 58122.6, "low_price": 58120.01, "base_asset_volume": 0.91011, "number_of_trades": 340, "is_kline_closed": true, "quote_asset_volume": 52896.2029873, "taker_buy_base_asset_volume": 0.07306, "taker_buy_quote_asset_volume": 4246.2486612, "ignore": "0"}]