[{"event_type": "kline", "event_time": 1720870321006, "symbol": "BTCUSDT", "kline_start_time": 1720870320000, "kline_close_time": 1720870320999, "interval": "1s", "first_trade_id": 3680341615, "last_trade_id": 3680341615, "open_price": 58514.0, "close_price": 58514.0, "high_price": 58514.0, "low_price": 58514.0, "base_asset_volume": 0.00418, "number_of_trades": 1, "is_kline_closed": true, "quote_asset_volume": 244.58852, "taker_buy_base_asset_volume": 0.00418, "taker_buy_quote_asset_volume": 244.58852, "ignore": "0"}, {"event_type": "kline", "event_time": 1720870322005, "symbol": "BTCUSDT", "kline_start_time": 1720870321000, "kline_close_time": 1720870321999, "interval": "1s", "first_trade_id": 3680341616, "last_trade_id": 3680341625, "open_price": 58513.99, "close_price": 58513.98, "high_price": 58513.99, "low_price": 58513.98, "base_asset_volume": 0.03244, "number_of_trades": 10, "is_kline_closed": true, "quote_asset_volume": 1898.1938347, "taker_buy_base_asset_volume": 0.0, "taker_buy_quote_asset_volume": 0.0, "ignore": "0"}, {"event_type": "kline", "event_time": 1720870323006, "symbol": "BTCUSDT", "kline_start_time": 1720870322000, "kline_close_time": 1720870322999, "interval": "1s", "first_trade_id": 3680341626, "last_trade_id": 3680341627, "open_price": 58513.79, "close_price": 58513.8, "high_price": 58513.8, "low_price": 58513.79, "base_asset_volume": 0.00227, "number_of_trades": 2, "is_kline_closed": true, "quote_asset_volume": 132.8263055, "taker_buy_base_asset_volume": 0.00022, "taker_buy_quote_asset_volume": 12.873036, "ignore": "0"}, {"event_type": "kline", "event_time": 1720870324006, "symbol": "BTCUSDT", "kline_start_time": 1720870323000, "kline_close_time": 1720870323999, "interval": "1s", "first_trade_id": 3680341628, "last_trade_id": 3680341662, "open_price": 58513.79, "close_price": 58509.39, "high_price": 58513.79, "low_price": 58509.39, "base_asset_volume": 0.04914, "number_of_trades": 35, "is_kline_closed": true, "quote_asset_volume": 2875.2068463, "taker_buy_base_asset_volume": 0.01647, "taker_buy_quote_asset_volume": 963.649818, "ignore": "0"}, {"event_type": "kline", "event_time": 1720870325006, "symbol": "BTCUSDT", "kline_start_time": 1720870324000, "kline_close_time": 1720870324999, "interval": "1s", "first_trade_id": 3680341663, "last_trade_id": 3680341672, "open_price": 58509.4, "close_price": 58510.0, "high_price": 58510.0, "low_price": 58509.4, "base_asset_volume": 0.0057, "number_of_trades": 10, "is_kline_closed": true, "quote_asset_volume": 333.504138, "taker_buy_base_asset_volume": 0.0057, "taker_buy_quote_asset_volume": 333.504138, "ignore": "0"}]