[{"event_type": "kline", "event_time": 1720869716005, "symbol": "BTCUSDT", "kline_start_time": 1720869715000, "kline_close_time": 1720869715999, "interval": "1s", "first_trade_id": -1, "last_trade_id": -1, "open_price": 58400.01, "close_price": 58400.01, "high_price": 58400.01, "low_price": 58400.01, "base_asset_volume": 0.0, "number_of_trades": 0, "is_kline_closed": true, "quote_asset_volume": 0.0, "taker_buy_base_asset_volume": 0.0, "taker_buy_quote_asset_volume": 0.0, "ignore": "0"}, {"event_type": "kline", "event_time": 1720869717005, "symbol": "BTCUSDT", "kline_start_time": 1720869716000, "kline_close_time": 1720869716999, "interval": "1s", "first_trade_id": 3680335731, "last_trade_id": 3680335732, "open_price": 58400.0, "close_price": 58400.0, "high_price": 58400.0, "low_price": 58400.0, "base_asset_volume": 0.00178, "number_of_trades": 2, "is_kline_closed": true, "quote_asset_volume": 103.952, "taker_buy_base_asset_volume": 0.0, "taker_buy_quote_asset_volume": 0.0, "ignore": "0"}, {"event_type": "kline", "event_time": 1720869718005, "symbol": "BTCUSDT", "kline_start_time": 1720869717000, "kline_close_time": 1720869717999, "interval": "1s", "first_trade_id": 3680335733, "last_trade_id": 3680335735, "open_price": 58400.0, "close_price": 58400.0, "high_price": 58400.0, "low_price": 58400.0, "base_asset_volume": 0.00724, "number_of_trades": 3, "is_kline_closed": true, "quote_asset_volume": 422.816, "taker_buy_base_asset_volume": 0.0, "taker_buy_quote_asset_volume": 0.0, "ignore": "0"}, {"event_type": "kline", "event_time": 1720869719006, "symbol": "BTCUSDT", "kline_start_time": 1720869718000, "kline_close_time": 1720869718999, "interval": "1s", "first_trade_id": 3680335736, "last_trade_id": 3680335751, "open_price": 58400.01, "close_price": 58400.0, "high_price": 58400.01, "low_price": 58400.0, "base_asset_volume": 0.04427, "number_of_trades": 16, "is_kline_closed": true, "quote_asset_volume": 2585.368428, "taker_buy_base_asset_volume": 0.0428, "taker_buy_quote_asset_volume": 2499.520428, "ignore": "0"}, {"event_type": "kline", "event_time": 1720869720006, "symbol": "BTCUSDT", "kline_start_time": 1720869719000, "kline_close_time": 1720869719999, "interval": "1s", "first_trade_id": 3680335752, "last_trade_id": 3680335759, "open_price": 58400.01, "close_price": 58400.01, "high_price": 58400.01, "low_price": 58400.0, "base_asset_volume": 0.17292, "number_of_trades": 8, "is_kline_closed": true, "quote_asset_volume": 10098.5289047, "taker_buy_base_asset_volume": 0.09047, "taker_buy_quote_asset_volume": 5283.4489047, "ignore": "0"}]