[{"event_type": "kline", "event_time": 1720216675006, "symbol": "BTCUSDT", "kline_start_time": 1720216674000, "kline_close_time": 1720216674999, "interval": "1s", "first_trade_id": 3667119660, "last_trade_id": 3667119660, "open_price": 56557.2, "close_price": 56557.2, "high_price": 56557.2, "low_price": 56557.2, "base_asset_volume": 0.21397, "number_of_trades": 1, "is_kline_closed": true, "quote_asset_volume": 12101.544084, "taker_buy_base_asset_volume": 0.21397, "taker_buy_quote_asset_volume": 12101.544084, "ignore": "0"}, {"event_type": "kline", "event_time": 1720216676006, "symbol": "BTCUSDT", "kline_start_time": 1720216675000, "kline_close_time": 1720216675999, "interval": "1s", "first_trade_id": 3667119661, "last_trade_id": 3667119665, "open_price": 56557.19, "close_price": 56557.19, "high_price": 56557.2, "low_price": 56557.19, "base_asset_volume": 0.00561, "number_of_trades": 5, "is_kline_closed": true, "quote_asset_volume": 317.2858376, "taker_buy_base_asset_volume": 0.00017, "taker_buy_quote_asset_volume": 9.614724, "ignore": "0"}, {"event_type": "kline", "event_time": 1720216677006, "symbol": "BTCUSDT", "kline_start_time": 1720216676000, "kline_close_time": 1720216676999, "interval": "1s", "first_trade_id": -1, "last_trade_id": -1, "open_price": 56557.19, "close_price": 56557.19, "high_price": 56557.19, "low_price": 56557.19, "base_asset_volume": 0.0, "number_of_trades": 0, "is_kline_closed": true, "quote_asset_volume": 0.0, "taker_buy_base_asset_volume": 0.0, "taker_buy_quote_asset_volume": 0.0, "ignore": "0"}, {"event_type": "kline", "event_time": 1720216678006, "symbol": "BTCUSDT", "kline_start_time": 1720216677000, "kline_close_time": 1720216677999, "interval": "1s", "first_trade_id": 3667119666, "last_trade_id": 3667119680, "open_price": 56557.2, "close_price": 56557.19, "high_price": 56557.2, "low_price": 56557.19, "base_asset_volume": 0.02495, "number_of_trades": 15, "is_kline_closed": true, "quote_asset_volume": 1411.1018975, "taker_buy_base_asset_volume": 0.0007, "taker_buy_quote_asset_volume": 39.59004, "ignore": "0"}, {"event_type": "kline", "event_time": 1720216679005, "symbol": "BTCUSDT", "kline_start_time": 1720216678000, "kline_close_time": 1720216678999, "interval": "1s", "first_trade_id": 3667119681, "last_trade_id": 3667119681, "open_price": 56557.2, "close_price": 56557.2, "high_price": 56557.2, "low_price": 56557.2, "base_asset_volume": 0.0016, "number_of_trades": 1, "is_kline_closed": true, "quote_asset_volume": 90.49152, "taker_buy_base_asset_volume": 0.0016, "taker_buy_quote_asset_volume": 90.49152, "ignore": "0"}, {"event_type": "kline", "event_time": 1720216680006, "symbol": "BTCUSDT", "kline_start_time": 1720216679000, "kline_close_time": 1720216679999, "interval": "1s", "first_trade_id": 3667119682, "last_trade_id": 3667119686, "open_price": 56557.2, "close_price": 56557.2, "high_price": 56557.2, "low_price": 56557.2, "base_asset_volume": 0.00972, "number_of_trades": 5, "is_kline_closed": true, "quote_asset_volume": 549.735984, "taker_buy_base_asset_volume": 0.00972, "taker_buy_quote_asset_volume": 549.735984, "ignore": "0"}, {"event_type": "kline", "event_time": 1720216681006, "symbol": "BTCUSDT", "kline_start_time": 1720216680000, "kline_close_time": 1720216680999, "interval": "1s", "first_trade_id": 3667119687, "last_trade_id": 3667119690, "open_price": 56557.19, "close_price": 56557.19, "high_price": 56557.19, "low_price": 56557.19, "base_asset_volume": 0.00975, "number_of_trades": 4, "is_kline_closed": true, "quote_asset_volume": 551.4326025, "taker_buy_base_asset_volume": 0.0, "taker_buy_quote_asset_volume": 0.0, "ignore": "0"}, {"event_type": "kline", "event_time": 1720216682006, "symbol": "BTCUSDT", "kline_start_time": 1720216681000, "kline_close_time": 1720216681999, "interval": "1s", "first_trade_id": 3667119691, "last_trade_id": 3667119694, "open_price": 56557.2, "close_price": 56557.19, "high_price": 56557.2, "low_price": 56557.19, "base_asset_volume": 0.00285, "number_of_trades": 4, "is_kline_closed": true, "quote_asset_volume": 161.1879965, "taker_buy_base_asset_volume": 0.0005, "taker_buy_quote_asset_volume": 28.2786, "ignore": "0"}, {"event_type": "kline", "event_time": 1720216683005, "symbol": "BTCUSDT", "kline_start_time": 1720216682000, "kline_close_time": 1720216682999, "interval": "1s", "first_trade_id": 3667119695, "last_trade_id": 3667119695, "open_price": 56557.19, "close_price": 56557.19, "high_price": 56557.19, "low_price": 56557.19, "base_asset_volume": 0.00022, "number_of_trades": 1, "is_kline_closed": true, "quote_asset_volume": 12.4425818, "taker_buy_base_asset_volume": 0.0, "taker_buy_quote_asset_volume": 0.0, "ignore": "0"}, {"event_type": "kline", "event_time": 1720216684006, "symbol": "BTCUSDT", "kline_start_time": 1720216683000, "kline_close_time": 1720216683999, "interval": "1s", "first_trade_id": 3667119696, "last_trade_id": 3667119698, "open_price": 56557.19, "close_price": 56557.19, "high_price": 56557.19, "low_price": 56557.19, "base_asset_volume": 0.00222, "number_of_trades": 3, "is_kline_closed": true, "quote_asset_volume": 125.5569618, "taker_buy_base_asset_volume": 0.0, "taker_buy_quote_asset_volume": 0.0, "ignore": "0"}, {"event_type": "kline", "event_time": 1720216685006, "symbol": "BTCUSDT", "kline_start_time": 1720216684000, "kline_close_time": 1720216684999, "interval": "1s", "first_trade_id": 3667119699, "last_trade_id": 3667119779, "open_price": 56557.19, "close_price": 56550.04, "high_price": 56557.19, "low_price": 56550.03, "base_asset_volume": 1.37717, "number_of_trades": 81, "is_kline_closed": true, "quote_asset_volume": 77883.5354498, "taker_buy_base_asset_volume": 0.28089, "taker_buy_quote_asset_volume": 15884.3407356, "ignore": "0"}, {"event_type": "kline", "event_time": 1720216686006, "symbol": "BTCUSDT", "kline_start_time": 1720216685000, "kline_close_time": 1720216685999, "interval": "1s", "first_trade_id": 3667119780, "last_trade_id": 3667119785, "open_price": 56550.04, "close_price": 56550.03, "high_price": 56550.04, "low_price": 56550.03, "base_asset_volume": 0.01769, "number_of_trades": 6, "is_kline_closed": true, "quote_asset_volume": 1000.3700547, "taker_buy_base_asset_volume": 0.0024, "taker_buy_quote_asset_volume": 135.720096, "ignore": "0"}, {"event_type": "kline", "event_time": 1720216687005, "symbol": "BTCUSDT", "kline_start_time": 1720216686000, "kline_close_time": 1720216686999, "interval": "1s", "first_trade_id": 3667119786, "last_trade_id": 3667119786, "open_price": 56550.04, "close_price": 56550.04, "high_price": 56550.04, "low_price": 56550.04, "base_asset_volume": 0.00042, "number_of_trades": 1, "is_kline_closed": true, "quote_asset_volume": 23.7510168, "taker_buy_base_asset_volume": 0.00042, "taker_buy_quote_asset_volume": 23.7510168, "ignore": "0"}, {"event_type": "kline", "event_time": 1720216688005, "symbol": "BTCUSDT", "kline_start_time": 1720216687000, "kline_close_time": 1720216687999, "interval": "1s", "first_trade_id": 3667119787, "last_trade_id": 3667119789, "open_price": 56550.04, "close_price": 56550.04, "high_price": 56550.04, "low_price": 56550.04, "base_asset_volume": 0.00449, "number_of_trades": 3, "is_kline_closed": true, "quote_asset_volume": 253.9096796, "taker_buy_base_asset_volume": 0.00449, "taker_buy_quote_asset_volume": 253.9096796, "ignore": "0"}, {"event_type": "kline", "event_time": 1720216689006, "symbol": "BTCUSDT", "kline_start_time": 1720216688000, "kline_close_time": 1720216688999, "interval": "1s", "first_trade_id": 3667119790, "last_trade_id": 3667119803, "open_price": 56550.03, "close_price": 56550.04, "high_price": 56550.04, "low_price": 56550.03, "base_asset_volume": 0.28166, "number_of_trades": 14, "is_kline_closed": true, "quote_asset_volume": 15927.8842306, "taker_buy_base_asset_volume": 0.27808, "taker_buy_quote_asset_volume": 15725.4351232, "ignore": "0"}, {"event_type": "kline", "event_time": 1720216690006, "symbol": "BTCUSDT", "kline_start_time": 1720216689000, "kline_close_time": 1720216689999, "interval": "1s", "first_trade_id": 3667119804, "last_trade_id": 3667119961, "open_price": 56550.9, "close_price": 56571.11, "high_price": 56571.11, "low_price": 56550.9, "base_asset_volume": 2.44304, "number_of_trades": 158, "is_kline_closed": true, "quote_asset_volume": 138186.5432159, "taker_buy_base_asset_volume": 2.44304, "taker_buy_quote_asset_volume": 138186.5432159, "ignore": "0"}, {"event_type": "kline", "event_time": 1720216691006, "symbol": "BTCUSDT", "kline_start_time": 1720216690000, "kline_close_time": 1720216690999, "interval": "1s", "first_trade_id": 3667119962, "last_trade_id": 3667119962, "open_price": 56571.1, "close_price": 56571.1, "high_price": 56571.1, "low_price": 56571.1, "base_asset_volume": 0.00023, "number_of_trades": 1, "is_kline_closed": true, "quote_asset_volume": 13.011353, "taker_buy_base_asset_volume": 0.0, "taker_buy_quote_asset_volume": 0.0, "ignore": "0"}, {"event_type": "kline", "event_time": 1720216692006, "symbol": "BTCUSDT", "kline_start_time": 1720216691000, "kline_close_time": 1720216691999, "interval": "1s", "first_trade_id": 3667119963, "last_trade_id": 3667119964, "open_price": 56571.1, "close_price": 56571.1, "high_price": 56571.1, "low_price": 56571.1, "base_asset_volume": 0.00793, "number_of_trades": 2, "is_kline_closed": true, "quote_asset_volume": 448.608823, "taker_buy_base_asset_volume": 0.0, "taker_buy_quote_asset_volume": 0.0, "ignore": "0"}, {"event_type": "kline", "event_time": 1720216693005, "symbol": "BTCUSDT", "kline_start_time": 1720216692000, "kline_close_time": 1720216692999, "interval": "1s", "first_trade_id": 3667119965, "last_trade_id": 3667119968, "open_price": 56571.1, "close_price": 56571.1, "high_price": 56571.1, "low_price": 56571.1, "base_asset_volume": 0.01641, "number_of_trades": 4, "is_kline_closed": true, "quote_asset_volume": 928.331751, "taker_buy_base_asset_volume": 0.0, "taker_buy_quote_asset_volume": 0.0, "ignore": "0"}, {"event_type": "kline", "event_time": 1720216694006, "symbol": "BTCUSDT", "kline_start_time": 1720216693000, "kline_close_time": 1720216693999, "interval": "1s", "first_trade_id": 3667119969, "last_trade_id": 3667119969, "open_price": 56571.11, "close_price": 56571.11, "high_price": 56571.11, "low_price": 56571.11, "base_asset_volume": 0.0053, "number_of_trades": 1, "is_kline_closed": true, "quote_asset_volume": 299.826883, "taker_buy_base_asset_volume": 0.0053, "taker_buy_quote_asset_volume": 299.826883, "ignore": "0"}]