[{"event_type": "kline", "event_time": 1720865445006, "symbol": "BTCUSDT", "kline_start_time": 1720865444000, "kline_close_time": 1720865444999, "interval": "1s", "first_trade_id": 3680290032, "last_trade_id": 3680290045, "open_price": 58741.25, "close_price": 58741.25, "high_price": 58741.26, "low_price": 58741.25, "base_asset_volume": 1.00086, "number_of_trades": 14, "is_kline_closed": true, "quote_asset_volume": 58791.7674792, "taker_buy_base_asset_volume": 0.00042, "taker_buy_quote_asset_volume": 24.6713292, "ignore": "0"}, {"event_type": "kline", "event_time": 1720865446006, "symbol": "BTCUSDT", "kline_start_time": 1720865445000, "kline_close_time": 1720865445999, "interval": "1s", "first_trade_id": 3680290046, "last_trade_id": 3680290051, "open_price": 58741.25, "close_price": 58741.25, "high_price": 58741.25, "low_price": 58741.25, "base_asset_volume": 0.07076, "number_of_trades": 6, "is_kline_closed": true, "quote_asset_volume": 4156.53085, "taker_buy_base_asset_volume": 0.0, "taker_buy_quote_asset_volume": 0.0, "ignore": "0"}, {"event_type": "kline", "event_time": 1720865447006, "symbol": "BTCUSDT", "kline_start_time": 1720865446000, "kline_close_time": 1720865446999, "interval": "1s", "first_trade_id": 3680290052, "last_trade_id": 3680290149, "open_price": 58741.25, "close_price": 58730.6, "high_price": 58741.25, "low_price": 58730.6, "base_asset_volume": 3.08138, "number_of_trades": 98, "is_kline_closed": true, "quote_asset_volume": 180994.5176016, "taker_buy_base_asset_volume": 0.0052, "taker_buy_quote_asset_volume": 305.399172, "ignore": "0"}, {"event_type": "kline", "event_time": 1720865448005, "symbol": "BTCUSDT", "kline_start_time": 1720865447000, "kline_close_time": 1720865447999, "interval": "1s", "first_trade_id": 3680290150, "last_trade_id": 3680290153, "open_price": 58730.6, "close_price": 58730.6, "high_price": 58730.61, "low_price": 58730.6, "base_asset_volume": 0.01023, "number_of_trades": 4, "is_kline_closed": true, "quote_asset_volume": 600.8140465, "taker_buy_base_asset_volume": 0.00085, "taker_buy_quote_asset_volume": 49.9210185, "ignore": "0"}, {"event_type": "kline", "event_time": 1720865449006, "symbol": "BTCUSDT", "kline_start_time": 1720865448000, "kline_close_time": 1720865448999, "interval": "1s", "first_trade_id": 3680290154, "last_trade_id": 3680290211, "open_price": 58730.61, "close_price": 58744.0, "high_price": 58744.0, "low_price": 58730.61, "base_asset_volume": 2.03407, "number_of_trades": 58, "is_kline_closed": true, "quote_asset_volume": 119472.028927, "taker_buy_base_asset_volume": 2.03293, "taker_buy_quote_asset_volume": 119405.0607784, "ignore": "0"}]