[{"event_type": "kline", "event_time": 1720870601005, "symbol": "BTCUSDT", "kline_start_time": 1720870600000, "kline_close_time": 1720870600999, "interval": "1s", "first_trade_id": 3680344596, "last_trade_id": 3680344596, "open_price": 58517.09, "close_price": 58517.09, "high_price": 58517.09, "low_price": 58517.09, "base_asset_volume": 0.01698, "number_of_trades": 1, "is_kline_closed": true, "quote_asset_volume": 993.6201882, "taker_buy_base_asset_volume": 0.01698, "taker_buy_quote_asset_volume": 993.6201882, "ignore": "0"}, {"event_type": "kline", "event_time": 1720870602006, "symbol": "BTCUSDT", "kline_start_time": 1720870601000, "kline_close_time": 1720870601999, "interval": "1s", "first_trade_id": 3680344597, "last_trade_id": 3680344600, "open_price": 58517.09, "close_price": 58517.08, "high_price": 58517.09, "low_price": 58517.08, "base_asset_volume": 0.00188, "number_of_trades": 4, "is_kline_closed": true, "quote_asset_volume": 110.0121138, "taker_buy_base_asset_volume": 0.00034, "taker_buy_quote_asset_volume": 19.8958106, "ignore": "0"}, {"event_type": "kline", "event_time": 1720870603005, "symbol": "BTCUSDT", "kline_start_time": 1720870602000, "kline_close_time": 1720870602999, "interval": "1s", "first_trade_id": 3680344601, "last_trade_id": 3680344603, "open_price": 58517.08, "close_price": 58517.08, "high_price": 58517.09, "low_price": 58517.08, "base_asset_volume": 0.00252, "number_of_trades": 3, "is_kline_closed": true, "quote_asset_volume": 147.463051, "taker_buy_base_asset_volume": 0.00094, "taker_buy_quote_asset_volume": 55.0060646, "ignore": "0"}, {"event_type": "kline", "event_time": 1720870604005, "symbol": "BTCUSDT", "kline_start_time": 1720870603000, "kline_close_time": 1720870603999, "interval": "1s", "first_trade_id": -1, "last_trade_id": -1, "open_price": 58517.08, "close_price": 58517.08, "high_price": 58517.08, "low_price": 58517.08, "base_asset_volume": 0.0, "number_of_trades": 0, "is_kline_closed": true, "quote_asset_volume": 0.0, "taker_buy_base_asset_volume": 0.0, "taker_buy_quote_asset_volume": 0.0, "ignore": "0"}, {"event_type": "kline", "event_time": 1720870605005, "symbol": "BTCUSDT", "kline_start_time": 1720870604000, "kline_close_time": 1720870604999, "interval": "1s", "first_trade_id": 3680344604, "last_trade_id": 3680344604, "open_price": 58517.09, "close_price": 58517.09, "high_price": 58517.09, "low_price": 58517.09, "base_asset_volume": 0.00011, "number_of_trades": 1, "is_kline_closed": true, "quote_asset_volume": 6.4368799, "taker_buy_base_asset_volume": 0.00011, "taker_buy_quote_asset_volume": 6.4368799, "ignore": "0"}]