[{"event_type": "kline", "event_time": 1720979674006, "symbol": "BTCUSDT", "kline_start_time": 1720979673000, "kline_close_time": 1720979673999, "interval": "1s", "first_trade_id": 3682096249, "last_trade_id": 3682096250, "open_price": 60004.31, "close_price": 60004.31, "high_price": 60004.31, "low_price": 60004.31, "base_asset_volume": 0.00271, "number_of_trades": 2, "is_kline_closed": true, "quote_asset_volume": 162.6116801, "taker_buy_base_asset_volume": 0.0, "taker_buy_quote_asset_volume": 0.0, "ignore": "0"}, {"event_type": "kline", "event_time": 1720979675006, "symbol": "BTCUSDT", "kline_start_time": 1720979674000, "kline_close_time": 1720979674999, "interval": "1s", "first_trade_id": 3682096251, "last_trade_id": 3682096251, "open_price": 60004.31, "close_price": 60004.31, "high_price": 60004.31, "low_price": 60004.31, "base_asset_volume": 0.01491, "number_of_trades": 1, "is_kline_closed": true, "quote_asset_volume": 894.6642621, "taker_buy_base_asset_volume": 0.0, "taker_buy_quote_asset_volume": 0.0, "ignore": "0"}, {"event_type": "kline", "event_time": 1720979676007, "symbol": "BTCUSDT", "kline_start_time": 1720979675000, "kline_close_time": 1720979675999, "interval": "1s", "first_trade_id": 3682096252, "last_trade_id": 3682096253, "open_price": 60004.32, "close_price": 60004.32, "high_price": 60004.32, "low_price": 60004.32, "base_asset_volume": 0.00763, "number_of_trades": 2, "is_kline_closed": true, "quote_asset_volume": 457.8329616, "taker_buy_base_asset_volume": 0.00763, "taker_buy_quote_asset_volume": 457.8329616, "ignore": "0"}, {"event_type": "kline", "event_time": 1720979677006, "symbol": "BTCUSDT", "kline_start_time": 1720979676000, "kline_close_time": 1720979676999, "interval": "1s", "first_trade_id": 3682096254, "last_trade_id": 3682096254, "open_price": 60004.31, "close_price": 60004.31, "high_price": 60004.31, "low_price": 60004.31, "base_asset_volume": 0.00237, "number_of_trades": 1, "is_kline_closed": true, "quote_asset_volume": 142.2102147, "taker_buy_base_asset_volume": 0.0, "taker_buy_quote_asset_volume": 0.0, "ignore": "0"}, {"event_type": "kline", "event_time": 1720979678006, "symbol": "BTCUSDT", "kline_start_time": 1720979677000, "kline_close_time": 1720979677999, "interval": "1s", "first_trade_id": 3682096255, "last_trade_id": 3682096258, "open_price": 60004.31, "close_price": 60004.32, "high_price": 60004.32, "low_price": 60004.31, "base_asset_volume": 0.00831, "number_of_trades": 4, "is_kline_closed": true, "quote_asset_volume": 498.6358311, "taker_buy_base_asset_volume": 0.0015, "taker_buy_quote_asset_volume": 90.00648, "ignore": "0"}, {"event_type": "kline", "event_time": 1720979679005, "symbol": "BTCUSDT", "kline_start_time": 1720979678000, "kline_close_time": 1720979678999, "interval": "1s", "first_trade_id": 3682096259, "last_trade_id": 3682096262, "open_price": 60004.31, "close_price": 60004.31, "high_price": 60004.32, "low_price": 60004.31, "base_asset_volume": 0.00719, "number_of_trades": 4, "is_kline_closed": true, "quote_asset_volume": 431.430999, "taker_buy_base_asset_volume": 0.00101, "taker_buy_quote_asset_volume": 60.6043632, "ignore": "0"}, {"event_type": "kline", "event_time": 1720979680006, "symbol": "BTCUSDT", "kline_start_time": 1720979679000, "kline_close_time": 1720979679999, "interval": "1s", "first_trade_id": -1, "last_trade_id": -1, "open_price": 60004.31, "close_price": 60004.31, "high_price": 60004.31, "low_price": 60004.31, "base_asset_volume": 0.0, "number_of_trades": 0, "is_kline_closed": true, "quote_asset_volume": 0.0, "taker_buy_base_asset_volume": 0.0, "taker_buy_quote_asset_volume": 0.0, "ignore": "0"}, {"event_type": "kline", "event_time": 1720979681006, "symbol": "BTCUSDT", "kline_start_time": 1720979680000, "kline_close_time": 1720979680999, "interval": "1s", "first_trade_id": -1, "last_trade_id": -1, "open_price": 60004.31, "close_price": 60004.31, "high_price": 60004.31, "low_price": 60004.31, "base_asset_volume": 0.0, "number_of_trades": 0, "is_kline_closed": true, "quote_asset_volume": 0.0, "taker_buy_base_asset_volume": 0.0, "taker_buy_quote_asset_volume": 0.0, "ignore": "0"}, {"event_type": "kline", "event_time": 1720979682006, "symbol": "BTCUSDT", "kline_start_time": 1720979681000, "kline_close_time": 1720979681999, "interval": "1s", "first_trade_id": 3682096263, "last_trade_id": 3682096309, "open_price": 60004.32, "close_price": 60009.62, "high_price": 60009.63, "low_price": 60004.32, "base_asset_volume": 0.20002, "number_of_trades": 47, "is_kline_closed": true, "quote_asset_volume": 12002.2191324, "taker_buy_base_asset_volume": 0.19893, "taker_buy_quote_asset_volume": 11936.8086466, "ignore": "0"}, {"event_type": "kline", "event_time": 1720979683006, "symbol": "BTCUSDT", "kline_start_time": 1720979682000, "kline_close_time": 1720979682999, "interval": "1s", "first_trade_id": -1, "last_trade_id": -1, "open_price": 60009.62, "close_price": 60009.62, "high_price": 60009.62, "low_price": 60009.62, "base_asset_volume": 0.0, "number_of_trades": 0, "is_kline_closed": true, "quote_asset_volume": 0.0, "taker_buy_base_asset_volume": 0.0, "taker_buy_quote_asset_volume": 0.0, "ignore": "0"}, {"event_type": "kline", "event_time": 1720979684005, "symbol": "BTCUSDT", "kline_start_time": 1720979683000, "kline_close_time": 1720979683999, "interval": "1s", "first_trade_id": 3682096310, "last_trade_id": 3682096311, "open_price": 60009.63, "close_price": 60009.63, "high_price": 60009.63, "low_price": 60009.63, "base_asset_volume": 0.00043, "number_of_trades": 2, "is_kline_closed": true, "quote_asset_volume": 25.8041409, "taker_buy_base_asset_volume": 0.00043, "taker_buy_quote_asset_volume": 25.8041409, "ignore": "0"}, {"event_type": "kline", "event_time": 1720979685005, "symbol": "BTCUSDT", "kline_start_time": 1720979684000, "kline_close_time": 1720979684999, "interval": "1s", "first_trade_id": -1, "last_trade_id": -1, "open_price": 60009.63, "close_price": 60009.63, "high_price": 60009.63, "low_price": 60009.63, "base_asset_volume": 0.0, "number_of_trades": 0, "is_kline_closed": true, "quote_asset_volume": 0.0, "taker_buy_base_asset_volume": 0.0, "taker_buy_quote_asset_volume": 0.0, "ignore": "0"}, {"event_type": "kline", "event_time": 1720979686005, "symbol": "BTCUSDT", "kline_start_time": 1720979685000, "kline_close_time": 1720979685999, "interval": "1s", "first_trade_id": 3682096312, "last_trade_id": 3682096313, "open_price": 60009.62, "close_price": 60009.63, "high_price": 60009.63, "low_price": 60009.62, "base_asset_volume": 0.00105, "number_of_trades": 2, "is_kline_closed": true, "quote_asset_volume": 63.0101086, "taker_buy_base_asset_volume": 0.00076, "taker_buy_quote_asset_volume": 45.6073188, "ignore": "0"}, {"event_type": "kline", "event_time": 1720979687006, "symbol": "BTCUSDT", "kline_start_time": 1720979686000, "kline_close_time": 1720979686999, "interval": "1s", "first_trade_id": -1, "last_trade_id": -1, "open_price": 60009.63, "close_price": 60009.63, "high_price": 60009.63, "low_price": 60009.63, "base_asset_volume": 0.0, "number_of_trades": 0, "is_kline_closed": true, "quote_asset_volume": 0.0, "taker_buy_base_asset_volume": 0.0, "taker_buy_quote_asset_volume": 0.0, "ignore": "0"}, {"event_type": "kline", "event_time": 1720979688007, "symbol": "BTCUSDT", "kline_start_time": 1720979687000, "kline_close_time": 1720979687999, "interval": "1s", "first_trade_id": 3682096314, "last_trade_id": 3682096314, "open_price": 60009.62, "close_price": 60009.62, "high_price": 60009.62, "low_price": 60009.62, "base_asset_volume": 0.00044, "number_of_trades": 1, "is_kline_closed": true, "quote_asset_volume": 26.4042328, "taker_buy_base_asset_volume": 0.0, "taker_buy_quote_asset_volume": 0.0, "ignore": "0"}, {"event_type": "kline", "event_time": 1720979689006, "symbol": "BTCUSDT", "kline_start_time": 1720979688000, "kline_close_time": 1720979688999, "interval": "1s", "first_trade_id": 3682096315, "last_trade_id": 3682096316, "open_price": 60009.63, "close_price": 60009.63, "high_price": 60009.63, "low_price": 60009.63, "base_asset_volume": 0.00291, "number_of_trades": 2, "is_kline_closed": true, "quote_asset_volume": 174.6280233, "taker_buy_base_asset_volume": 0.00291, "taker_buy_quote_asset_volume": 174.6280233, "ignore": "0"}, {"event_type": "kline", "event_time": 1720979690006, "symbol": "BTCUSDT", "kline_start_time": 1720979689000, "kline_close_time": 1720979689999, "interval": "1s", "first_trade_id": 3682096317, "last_trade_id": 3682096317, "open_price": 60009.63, "close_price": 60009.63, "high_price": 60009.63, "low_price": 60009.63, "base_asset_volume": 0.00066, "number_of_trades": 1, "is_kline_closed": true, "quote_asset_volume": 39.6063558, "taker_buy_base_asset_volume": 0.00066, "taker_buy_quote_asset_volume": 39.6063558, "ignore": "0"}, {"event_type": "kline", "event_time": 1720979691006, "symbol": "BTCUSDT", "kline_start_time": 1720979690000, "kline_close_time": 1720979690999, "interval": "1s", "first_trade_id": 3682096318, "last_trade_id": 3682096319, "open_price": 60009.62, "close_price": 60009.63, "high_price": 60009.63, "low_price": 60009.62, "base_asset_volume": 0.00114, "number_of_trades": 2, "is_kline_closed": true, "quote_asset_volume": 68.4109735, "taker_buy_base_asset_volume": 0.00067, "taker_buy_quote_asset_volume": 40.2064521, "ignore": "0"}, {"event_type": "kline", "event_time": 1720979692006, "symbol": "BTCUSDT", "kline_start_time": 1720979691000, "kline_close_time": 1720979691999, "interval": "1s", "first_trade_id": -1, "last_trade_id": -1, "open_price": 60009.63, "close_price": 60009.63, "high_price": 60009.63, "low_price": 60009.63, "base_asset_volume": 0.0, "number_of_trades": 0, "is_kline_closed": true, "quote_asset_volume": 0.0, "taker_buy_base_asset_volume": 0.0, "taker_buy_quote_asset_volume": 0.0, "ignore": "0"}, {"event_type": "kline", "event_time": 1720979693005, "symbol": "BTCUSDT", "kline_start_time": 1720979692000, "kline_close_time": 1720979692999, "interval": "1s", "first_trade_id": 3682096320, "last_trade_id": 3682096320, "open_price": 60009.62, "close_price": 60009.62, "high_price": 60009.62, "low_price": 60009.62, "base_asset_volume": 0.00859, "number_of_trades": 1, "is_kline_closed": true, "quote_asset_volume": 515.4826358, "taker_buy_base_asset_volume": 0.0, "taker_buy_quote_asset_volume": 0.0, "ignore": "0"}]