[{"event_type": "kline", "event_time": 1720866196007, "symbol": "BTCUSDT", "kline_start_time": 1720866195000, "kline_close_time": 1720866195999, "interval": "1s", "first_trade_id": 3680298656, "last_trade_id": 3680298657, "open_price": 58700.01, "close_price": 58700.01, "high_price": 58700.01, "low_price": 58700.01, "base_asset_volume": 0.00319, "number_of_trades": 2, "is_kline_closed": true, "quote_asset_volume": 187.2530319, "taker_buy_base_asset_volume": 0.00319, "taker_buy_quote_asset_volume": 187.2530319, "ignore": "0"}, {"event_type": "kline", "event_time": 1720866197007, "symbol": "BTCUSDT", "kline_start_time": 1720866196000, "kline_close_time": 1720866196999, "interval": "1s", "first_trade_id": 3680298658, "last_trade_id": 3680298658, "open_price": 58700.0, "close_price": 58700.0, "high_price": 58700.0, "low_price": 58700.0, "base_asset_volume": 0.0033, "number_of_trades": 1, "is_kline_closed": true, "quote_asset_volume": 193.71, "taker_buy_base_asset_volume": 0.0, "taker_buy_quote_asset_volume": 0.0, "ignore": "0"}, {"event_type": "kline", "event_time": 1720866198007, "symbol": "BTCUSDT", "kline_start_time": 1720866197000, "kline_close_time": 1720866197999, "interval": "1s", "first_trade_id": 3680298659, "last_trade_id": 3680298660, "open_price": 58700.0, "close_price": 58700.0, "high_price": 58700.0, "low_price": 58700.0, "base_asset_volume": 0.00051, "number_of_trades": 2, "is_kline_closed": true, "quote_asset_volume": 29.937, "taker_buy_base_asset_volume": 0.0, "taker_buy_quote_asset_volume": 0.0, "ignore": "0"}, {"event_type": "kline", "event_time": 1720866199005, "symbol": "BTCUSDT", "kline_start_time": 1720866198000, "kline_close_time": 1720866198999, "interval": "1s", "first_trade_id": 3680298661, "last_trade_id": 3680298661, "open_price": 58700.0, "close_price": 58700.0, "high_price": 58700.0, "low_price": 58700.0, "base_asset_volume": 0.00163, "number_of_trades": 1, "is_kline_closed": true, "quote_asset_volume": 95.681, "taker_buy_base_asset_volume": 0.0, "taker_buy_quote_asset_volume": 0.0, "ignore": "0"}, {"event_type": "kline", "event_time": 1720866200006, "symbol": "BTCUSDT", "kline_start_time": 1720866199000, "kline_close_time": 1720866199999, "interval": "1s", "first_trade_id": 3680298662, "last_trade_id": 3680298719, "open_price": 58700.0, "close_price": 58700.0, "high_price": 58700.0, "low_price": 58700.0, "base_asset_volume": 0.02313, "number_of_trades": 58, "is_kline_closed": true, "quote_asset_volume": 1357.731, "taker_buy_base_asset_volume": 0.0, "taker_buy_quote_asset_volume": 0.0, "ignore": "0"}]